empty_storage/empty_storage/empty_storage.py
empty_storage/empty_storage/empty_storage.rego
empty_storage/empty_storage/manifest.toml
empty_storage/empty_storage/test_empty_storage.py
rds_idle/rds_idle/manifest.toml
rds_idle/rds_idle/rds_idle.py
rds_idle/rds_idle/rds_idle.rego
rds_idle/rds_idle/test_rds_idle.py
rds_old_snapshots/rds_old_snapshots/manifest.toml
rds_old_snapshots/rds_old_snapshots/rds_old_snapshots.py
rds_old_snapshots/rds_old_snapshots/rds_old_snapshots.rego
rds_old_snapshots/rds_old_snapshots/test_rds_old_snapshots.py
scaling_down/scaling_down/manifest.toml
scaling_down/scaling_down/scaling_down.py
scaling_down/scaling_down/scaling_down.rego
scaling_down/scaling_down/test_scaling_down.py
opsbox_rds_checks-0.2.0.dist-info/LICENCE.txt
opsbox_rds_checks-0.2.0.dist-info/METADATA
opsbox_rds_checks-0.2.0.dist-info/WHEEL
opsbox_rds_checks-0.2.0.dist-info/entry_points.txt
opsbox_rds_checks-0.2.0.dist-info/top_level.txt
opsbox_rds_checks-0.2.0.dist-info/RECORD
