Metadata-Version: 2.2
Name: opsbox-rds-checks
Version: 0.2.0
Summary: Collection of RDS checks for opsbox
License: Mozilla Public License Version 2.0
Requires-Python: ==3.11.*
License-File: LICENCE.txt
Requires-Dist: opsbox-rds-provider>=0.1.3
Requires-Dist: opsbox-rego-handler>=0.2.0
